PyWindowsCMD/__init__.py
PyWindowsCMD/errors.py
PyWindowsCMD/utilities.py
PyWindowsCMD/netstat/__init__.py
PyWindowsCMD/netstat/command.py
PyWindowsCMD/shutdown/__init__.py
PyWindowsCMD/shutdown/command.py
PyWindowsCMD/shutdown/parameters.py
PyWindowsCMD/taskkill/__init__.py
PyWindowsCMD/taskkill/command.py
PyWindowsCMD/taskkill/parameters.py
pywindowscmd-1.3.8.dist-info/METADATA
pywindowscmd-1.3.8.dist-info/WHEEL
pywindowscmd-1.3.8.dist-info/top_level.txt
pywindowscmd-1.3.8.dist-info/RECORD
