Metadata-Version: 2.2
Name: PyWindowsCMD
Version: 1.3.8
Summary: A Python library to simplify working with Windows command-line utilities like `netstat`, `shutdown`, and `taskkill`, providing structured output and a convenient interface.
Author: oddshellnick
Author-email: oddshellnick.programming@gmail.com
Requires-Dist: setuptools>=75.1.0
Requires-Dist: pandas>=2.2.3
Requires-Dist: pyvartools>=1.4.1
Dynamic: author
Dynamic: author-email
Dynamic: description
Dynamic: description-content-type
Dynamic: requires-dist
Dynamic: summary
